data_tasks/__init__.py
data_tasks/loader.py
data_tasks/python_script.py
data_tasks/sql_query.py
data_tasks/sql_script.py
data_tasks/timer.py
data_tasks-0.0.5.dist-info/LICENSE
data_tasks-0.0.5.dist-info/METADATA
data_tasks-0.0.5.dist-info/WHEEL
data_tasks-0.0.5.dist-info/top_level.txt
data_tasks-0.0.5.dist-info/RECORD
