Metadata-Version: 2.2
Name: data-tasks
Version: 0.0.5
Summary: Small library to run data related scripts
Home-page: https://github.com/hypothesis/data-tasks
Project-URL: Bug Tracker, https://github.com/hypothesis/data-tasks/issues
Project-URL: Changelog, https://github.com/hypothesis/data-tasks/releases
Classifier: Programming Language :: Python :: 3
Classifier: License :: OSI Approved :: BSD License
Classifier: Intended Audience :: Developers
Requires-Python: >=3.9
License-File: LICENSE
Requires-Dist: sqlalchemy
Requires-Dist: psycopg2
Requires-Dist: importlib_resources
Requires-Dist: jinja2
Requires-Dist: sqlparse
Requires-Dist: tabulate
